excellikeuno/__init__.py
excellikeuno/connection/__init__.py
excellikeuno/connection/bootstrap.py
excellikeuno/core/__init__.py
excellikeuno/core/base.py
excellikeuno/core/calc_document.py
excellikeuno/core/interfaces.py
excellikeuno/core/writer_document.py
excellikeuno/drawing/__init__.py
excellikeuno/drawing/closed_bezier_shape.py
excellikeuno/drawing/connector_shape.py
excellikeuno/drawing/control_shape.py
excellikeuno/drawing/custom_shape.py
excellikeuno/drawing/ellipse_shape.py
excellikeuno/drawing/fill_properties.py
excellikeuno/drawing/group_shape.py
excellikeuno/drawing/line_properties.py
excellikeuno/drawing/line_shape.py
excellikeuno/drawing/measure_shape.py
excellikeuno/drawing/open_bezier_shape.py
excellikeuno/drawing/page_shape.py
excellikeuno/drawing/polyline_shape.py
excellikeuno/drawing/polypolygon_bezier_shape.py
excellikeuno/drawing/polypolygon_shape.py
excellikeuno/drawing/rectangle_shape.py
excellikeuno/drawing/shadow_properties.py
excellikeuno/drawing/shape.py
excellikeuno/drawing/text_properties.py
excellikeuno/drawing/text_shape.py
excellikeuno/style/__init__.py
excellikeuno/style/border.py
excellikeuno/style/character_properties.py
excellikeuno/style/font.py
excellikeuno/style/line.py
excellikeuno/table/__init__.py
excellikeuno/table/cell.py
excellikeuno/table/cell_properties.py
excellikeuno/table/columns.py
excellikeuno/table/range.py
excellikeuno/table/rows.py
excellikeuno/table/sheet.py
excellikeuno/typing/__init__.py
excellikeuno/typing/calc.py
excellikeuno/typing/interfaces.py
excellikeuno/typing/structs.py
excellikeuno/utils/__init__.py
excellikeuno-0.2.0.dist-info/METADATA
excellikeuno-0.2.0.dist-info/WHEEL
excellikeuno-0.2.0.dist-info/top_level.txt
excellikeuno-0.2.0.dist-info/RECORD
