Metadata-Version: 2.4
Name: excellikeuno
Version: 0.2.0
Summary: Excel/VBA-like UNO wrapper for LibreOffice Calc and Writer
Author-email: Tomoaki Masuda <masuda@moonmile.net>
License: MIT
Project-URL: Homepage, https://github.com/moonmile/ExcelLikeUno
Keywords: libreoffice,uno,calc,writer,excel,vba
Classifier: Programming Language :: Python
Classifier: License :: OSI Approved :: MIT License
Classifier: Operating System :: OS Independent
Requires-Python: >=3.8
